denial/__init__.py
denial/inner.py
denial/py.typed
denial/sentinel_type.py
denial-0.0.8.dist-info/LICENSE
denial-0.0.8.dist-info/METADATA
denial-0.0.8.dist-info/WHEEL
denial-0.0.8.dist-info/top_level.txt
denial-0.0.8.dist-info/RECORD
